st_workflow/__init__.py
st_workflow-0.2.4.dist-info/METADATA
st_workflow-0.2.4.dist-info/WHEEL
st_workflow-0.2.4.dist-info/RECORD
