Metadata-Version: 2.1
Name: st_workflow
Version: 0.2.4
Summary: Library for creating complex workflows in Python
Home-page: https://github.com/safari12/st_workflow
License: MIT
Author: Reza Safari
Author-email: rsafari.s@gmail.com
Requires-Python: >=3.10,<4.0
Classifier: License :: OSI Approved :: MIT License
Classifier: Programming Language :: Python :: 3
Classifier: Programming Language :: Python :: 3.10
Classifier: Programming Language :: Python :: 3.11
Classifier: Programming Language :: Python :: 3.12
Requires-Dist: pytest (>=7.4.0,<8.0.0)
Project-URL: Repository, https://github.com/safari12/st_workflow
